better_test/__init__.py
better_test/compat.py
better_test/core.py
better_test/database.py
better_test/models.py
better_test/parallel.py
better_test/utils.py
better_test/harness/__init__.py
better_test/harness/basic.py
better_test/harness/crash.py
better_test/harness/isolate.py
better_test/harness/skip.py
better_test/management/__init__.py
better_test/management/commands/__init__.py
better_test/management/commands/test.py
better_test/management/commands/testinfo.py
better_test/tests/__init__.py
better_test/tests/test_basic.py
better_test/tests/test_crash.py
better_test/tests/test_isolate.py
django_better_test-0.10.dist-info/DESCRIPTION.rst
django_better_test-0.10.dist-info/METADATA
django_better_test-0.10.dist-info/RECORD
django_better_test-0.10.dist-info/WHEEL
django_better_test-0.10.dist-info/metadata.json
django_better_test-0.10.dist-info/top_level.txt
